staticXYZ/__init__.py
staticXYZ/__main__.py
staticXYZ-0.0.2.data/scripts/xyz
staticXYZ-0.0.2.dist-info/METADATA
staticXYZ-0.0.2.dist-info/WHEEL
staticXYZ-0.0.2.dist-info/entry_points.txt
staticXYZ-0.0.2.dist-info/top_level.txt
staticXYZ-0.0.2.dist-info/RECORD
